[
  {
    "id" : 1,
    "site_id" : -1,
    "created" : 1609459200,
    "activates" : 1609459200,
    "expires" : 1893456000,
    "secret" : "2m4mNGTExXEq7IoIB6ZpKRB2NmdGP2grhsuHsKiziKQ="
  },
  {
    "id" : 2,
    "site_id" : -2,
    "created" : 1609459200,
    "activates" : 1609459200,
    "expires" : 1893456000,
    "secret" : "c2yMYeezHfDvZ6haknCFaj0t+eAEJp/C/uh+fUAm1fo="
  },
  {
    "id" : 3,
    "site_id" : 2,
    "created" : 1609459200,
    "activates" : 1609459200,
    "expires" : 1893456000,
    "secret" : "RgyxkP4yP1gYhCINq7O9PxM6jX+etPqSQluZxjB1aG8="
  },
  {
    "id" : 4,
    "site_id" : 123,
    "created" : 1609459200,
    "activates" : 1609459200,
    "expires" : 1893456000,
    "secret" : "bVZZOwCuO0fUf2P6CrwaY23erMErVQiMkGgpy2OMSxc="
  },
  {
    "id" : 5,
    "site_id" : 124,
    "created" : 1609459200,
    "activates" : 1609459200,
    "expires" : 1893456000,
    "secret" : "zpxOafFdffTpeYFvaWnJlaLzJNzk+6qi77U2Umh7QJ4="
  },
  {
    "id" : 6,
    "site_id" : 125,
    "created" : 1609459200,
    "activates" : 1609459200,
    "expires" : 1893456000,
    "secret" : "juOszwVqEU3D7s4KrcckNRmk0uO3ePQX21UzSr8I7tU="
  }
]